{
  "project_info": {
    "project_number": "856502199604",
    "firebase_url": "https://ascii-paint.firebaseio.com",
    "project_id": "ascii-paint",
    "storage_bucket": "ascii-paint.appspot.com"
  },
  "client": [
    {
      "client_info": {
        "mobilesdk_app_id": "1:856502199604:android:163a67d274a5d47f",
        "android_client_info": {
          "package_name": "com.mrdeveloper.asciipaint"
        }
      },
      "oauth_client": [
        {
          "client_id": "856502199604-0cb25tgcb3lj10solc28rsg6tqpc0j09.apps.googleusercontent.com",
          "client_type": 3
        }
      ],
      "api_key": [
        {
          "current_key": "AIzaSyAA7JWWHFrLwBIU-tKcpqtRIps1enIe5hg"
        }
      ],
      "services": {
        "analytics_service": {
          "status": 1
        },
        "appinvite_service": {
          "status": 1,
          "other_platform_oauth_client": []
        },
        "ads_service": {
          "status": 2
        }
      }
    }
  ],
  "configuration_version": "1"
}